example/__init__.py
yxtree/__init__.py
yxtree/cli.py
yxtree/versions.py
yxtree/src/__init__.py
yxtree/src/pipeline.py
yxtree/src/tree.py
yxtree/src/utils.py
yxtree/src/plot/__init__.py
yxtree/src/plot/circular.py
yxtree/src/plot/rectangular.py
yxtree/src/plot/unrooted.py
yxtree-0.0.4.dist-info/LICENSE
yxtree-0.0.4.dist-info/METADATA
yxtree-0.0.4.dist-info/WHEEL
yxtree-0.0.4.dist-info/entry_points.txt
yxtree-0.0.4.dist-info/top_level.txt
yxtree-0.0.4.dist-info/RECORD
