Metadata-Version: 2.1
Name: yxtree
Version: 0.0.4
Summary: Here's an example of a repository
Home-page: https://github.com/SouthernCD/yxtree
Author: Yuxing Xu
Author-email: xuyuxing@mail.kib.ac.cn
Requires-Python: >=3.5
License-File: LICENSE
Requires-Dist: yxutil
Requires-Dist: yxmath >=0.0.5
Requires-Dist: matplotlib >=3.5.0
Requires-Dist: networkx >=2.4
Requires-Dist: biopython <=1.80
Requires-Dist: numpy >=1.18.1
